README.md
setup.py
PrismNET/__init__.py
PrismNET/packager.py
PrismNET.egg-info/PKG-INFO
PrismNET.egg-info/SOURCES.txt
PrismNET.egg-info/dependency_links.txt
PrismNET.egg-info/requires.txt
PrismNET.egg-info/top_level.txt