Metadata-Version: 2.1
Name: PrismNET
Version: 0.10.0
Summary: A easy framework..
Home-page: https://github.com/Microbots-io/PrismNet-Framework/tree/main
Author: frane s 
Author-email: znikafranek@gmail.com
Classifier: Programming Language :: Python :: 3
Classifier: License :: OSI Approved :: MIT License
Classifier: Operating System :: OS Independent
Classifier: Topic :: Software Development :: Libraries :: Python Modules
Requires-Dist: pyinstaller
Requires-Dist: setuptools
Requires-Dist: wheel
